aider/__init__.py
aider/__main__.py
aider/args.py
aider/args_formatter.py
aider/commands.py
aider/diffs.py
aider/dump.py
aider/gui.py
aider/help.py
aider/help_pats.py
aider/history.py
aider/io.py
aider/linter.py
aider/llm.py
aider/main.py
aider/mdstream.py
aider/models.py
aider/prompts.py
aider/repo.py
aider/repomap.py
aider/scrape.py
aider/sendchat.py
aider/urls.py
aider/utils.py
aider/versioncheck.py
aider/voice.py
aider/coders/__init__.py
aider/coders/base_coder.py
aider/coders/base_prompts.py
aider/coders/editblock_coder.py
aider/coders/editblock_fenced_coder.py
aider/coders/editblock_fenced_prompts.py
aider/coders/editblock_func_coder.py
aider/coders/editblock_func_prompts.py
aider/coders/editblock_prompts.py
aider/coders/help_coder.py
aider/coders/help_prompts.py
aider/coders/search_replace.py
aider/coders/single_wholefile_func_coder.py
aider/coders/single_wholefile_func_prompts.py
aider/coders/udiff_coder.py
aider/coders/udiff_prompts.py
aider/coders/wholefile_coder.py
aider/coders/wholefile_func_coder.py
aider/coders/wholefile_func_prompts.py
aider/coders/wholefile_prompts.py
aider/tests/__init__.py
aider/tests/test_coder.py
aider/tests/test_commands.py
aider/tests/test_editblock.py
aider/tests/test_help.py
aider/tests/test_io.py
aider/tests/test_main.py
aider/tests/test_models.py
aider/tests/test_repo.py
aider/tests/test_repomap.py
aider/tests/test_sendchat.py
aider/tests/test_udiff.py
aider/tests/test_urls.py
aider/tests/test_wholefile.py
test4488-4.16.dist-info/LICENSE.txt
test4488-4.16.dist-info/METADATA
test4488-4.16.dist-info/WHEEL
test4488-4.16.dist-info/entry_points.txt
test4488-4.16.dist-info/top_level.txt
test4488-4.16.dist-info/RECORD
