Metadata-Version: 2.1
Name: test4488
Version: 4.16
Summary: AI Software Engineer
Requires-Python: >=3.9,<3.13
License-File: LICENSE.txt
Requires-Dist: aiohttp==3.9.5
Requires-Dist: aiosignal==1.3.1
Requires-Dist: altair==5.3.0
Requires-Dist: annotated-types==0.7.0
Requires-Dist: anyio==4.4.0
Requires-Dist: attrs==23.2.0
Requires-Dist: backoff==2.2.1
Requires-Dist: beautifulsoup4==4.12.3
Requires-Dist: blinker==1.8.2
Requires-Dist: cachetools==5.3.3
Requires-Dist: certifi==2024.7.4
Requires-Dist: cffi==1.16.0
Requires-Dist: charset-normalizer==3.3.2
Requires-Dist: click==8.1.7
Requires-Dist: configargparse==1.7
Requires-Dist: dataclasses-json==0.6.7
Requires-Dist: deprecated==1.2.14
Requires-Dist: diff-match-patch==20230430
Requires-Dist: dirtyjson==1.0.8
Requires-Dist: diskcache==5.6.3
Requires-Dist: distro==1.9.0
Requires-Dist: filelock==3.15.4
Requires-Dist: flake8==7.1.0
Requires-Dist: frozenlist==1.4.1
Requires-Dist: fsspec==2024.6.1
Requires-Dist: gitdb==4.0.11
Requires-Dist: gitpython==3.1.43
Requires-Dist: google-ai-generativelanguage==0.6.6
Requires-Dist: google-api-core[grpc]==2.19.1
Requires-Dist: google-api-python-client==2.136.0
Requires-Dist: google-auth==2.31.0
Requires-Dist: google-auth-httplib2==0.2.0
Requires-Dist: google-generativeai==0.7.1
Requires-Dist: googleapis-common-protos==1.63.2
Requires-Dist: greenlet==3.0.3
Requires-Dist: grep-ast==0.3.2
Requires-Dist: grpcio==1.64.1
Requires-Dist: grpcio-status==1.62.2
Requires-Dist: h11==0.14.0
Requires-Dist: httpcore==1.0.5
Requires-Dist: httplib2==0.22.0
Requires-Dist: httpx==0.27.0
Requires-Dist: huggingface-hub[inference]==0.23.4
Requires-Dist: idna==3.7
Requires-Dist: importlib-metadata==7.2.1
Requires-Dist: importlib-resources==6.4.0
Requires-Dist: jinja2==3.1.4
Requires-Dist: joblib==1.4.2
Requires-Dist: jsonschema==4.22.0
Requires-Dist: jsonschema-specifications==2023.12.1
Requires-Dist: litellm==1.41.6
Requires-Dist: llama-cloud==0.0.6
Requires-Dist: llama-index-core==0.10.52.post2
Requires-Dist: llama-index-embeddings-huggingface==0.2.2
Requires-Dist: markdown-it-py==3.0.0
Requires-Dist: markupsafe==2.1.5
Requires-Dist: marshmallow==3.21.3
Requires-Dist: mccabe==0.7.0
Requires-Dist: mdurl==0.1.2
Requires-Dist: minijinja==2.0.1
Requires-Dist: mpmath==1.3.0
Requires-Dist: multidict==6.0.5
Requires-Dist: mypy-extensions==1.0.0
Requires-Dist: nest-asyncio==1.6.0
Requires-Dist: networkx==3.2.1
Requires-Dist: nltk==3.8.1
Requires-Dist: numpy==1.26.4
Requires-Dist: openai==1.35.10
Requires-Dist: packaging==24.1
Requires-Dist: pandas==2.2.2
Requires-Dist: pathspec==0.12.1
Requires-Dist: pillow==10.4.0
Requires-Dist: playwright==1.45.0
Requires-Dist: prompt-toolkit==3.0.47
Requires-Dist: proto-plus==1.24.0
Requires-Dist: protobuf==4.25.3
Requires-Dist: pyarrow==16.1.0
Requires-Dist: pyasn1==0.6.0
Requires-Dist: pyasn1-modules==0.4.0
Requires-Dist: pycodestyle==2.12.0
Requires-Dist: pycparser==2.22
Requires-Dist: pydantic==2.8.2
Requires-Dist: pydantic-core==2.20.1
Requires-Dist: pydeck==0.9.1
Requires-Dist: pyee==11.1.0
Requires-Dist: pyflakes==3.2.0
Requires-Dist: pygments==2.18.0
Requires-Dist: pypandoc==1.13
Requires-Dist: pyparsing==3.1.2
Requires-Dist: python-dateutil==2.9.0.post0
Requires-Dist: python-dotenv==1.0.1
Requires-Dist: pytz==2024.1
Requires-Dist: pyyaml==6.0.1
Requires-Dist: referencing==0.35.1
Requires-Dist: regex==2024.5.15
Requires-Dist: requests==2.32.3
Requires-Dist: rich==13.7.1
Requires-Dist: rpds-py==0.18.1
Requires-Dist: rsa==4.9
Requires-Dist: safetensors==0.4.3
Requires-Dist: scikit-learn==1.5.1
Requires-Dist: scipy==1.13.1
Requires-Dist: sentence-transformers==3.0.1
Requires-Dist: six==1.16.0
Requires-Dist: smmap==5.0.1
Requires-Dist: sniffio==1.3.1
Requires-Dist: sounddevice==0.4.7
Requires-Dist: soundfile==0.12.1
Requires-Dist: soupsieve==2.5
Requires-Dist: sqlalchemy[asyncio]==2.0.31
Requires-Dist: streamlit==1.36.0
Requires-Dist: sympy==1.12.1
Requires-Dist: tenacity==8.4.2
Requires-Dist: threadpoolctl==3.5.0
Requires-Dist: tiktoken==0.7.0
Requires-Dist: tokenizers==0.19.1
Requires-Dist: toml==0.10.2
Requires-Dist: toolz==0.12.1
Requires-Dist: torch==2.2.2
Requires-Dist: tornado==6.4.1
Requires-Dist: tqdm==4.66.4
Requires-Dist: transformers==4.42.3
Requires-Dist: tree-sitter==0.21.3
Requires-Dist: tree-sitter-languages==1.10.2
Requires-Dist: typing-extensions==4.12.2
Requires-Dist: typing-inspect==0.9.0
Requires-Dist: tzdata==2024.1
Requires-Dist: uritemplate==4.1.1
Requires-Dist: urllib3==2.2.2
Requires-Dist: watchdog==4.0.1
Requires-Dist: wcwidth==0.2.13
Requires-Dist: wrapt==1.16.0
Requires-Dist: yarl==1.9.4
Requires-Dist: zipp==3.19.2
